dulcinea/colored_output.py
dulcinea/dulcinea.py
dulcinea/metadata.py
dulcinea/simple_output.py
etna_dulcinea-3.1.0.dist-info/METADATA
etna_dulcinea-3.1.0.dist-info/WHEEL
etna_dulcinea-3.1.0.dist-info/entry_points.txt
etna_dulcinea-3.1.0.dist-info/top_level.txt
etna_dulcinea-3.1.0.dist-info/RECORD
