Metadata-Version: 2.1
Name: etna-dulcinea
Version: 3.1.0
Summary: Script to test Quixote moulinettes locally
Home-page: https://github.com/etna-alternance/dulcinea
Author: Clément Doumergue
Author-email: clement.doumergue@etna.io
License: UNKNOWN
Platform: UNKNOWN
Classifier: Programming Language :: Python :: 3
Classifier: License :: OSI Approved :: MIT License
Classifier: Operating System :: OS Independent
Requires-Dist: etna-quixote (==2.*,>=2.0.0)
Requires-Dist: etna-panza (==4.*,>=4.1.0)
Requires-Dist: rich (~=9.10.0)
